README.rst
setup.py
Thunderargs.egg-info/SOURCES.txt
thunderargs/__init__.py
thunderargs/endpoint.py
thunderargs/errors.py
thunderargs/helpers.py
thunderargs/validfarm.py
thunderargs.egg-info/PKG-INFO
thunderargs.egg-info/SOURCES.txt
thunderargs.egg-info/dependency_links.txt
thunderargs.egg-info/top_level.txt