Metadata-Version: 1.0
Name: thunderargs
Version: 0.3.1
Summary: Let you use function annotations (PEP 3107) to parseand validate arguments
Home-page: https://bitbucket.org/dsupiev/thunderargs
Author: uthunderbird
Author-email: undead.thunderbird@gmail.com
License: JSON license
Platform: UNKNOWN
